{
  "db_name": "PostgreSQL",
  "query": "SELECT on_chain_hash, is_frozen, is_closed FROM program_state WHERE program_id = $1",
  "describe": {
    "columns": [
      {
        "ordinal": 0,
        "name": "on_chain_hash",
        "type_info": "Text",
        "origin": {
          "Table": {
            "table": "program_state",
            "name": "on_chain_hash"
          }
        }
      },
      {
        "ordinal": 1,
        "name": "is_frozen",
        "type_info": "Bool",
        "origin": {
          "Table": {
            "table": "program_state",
            "name": "is_frozen"
          }
        }
      },
      {
        "ordinal": 2,
        "name": "is_closed",
        "type_info": "Bool",
        "origin": {
          "Table": {
            "table": "program_state",
            "name": "is_closed"
          }
        }
      }
    ],
    "parameters": {
      "Left": [
        "Text"
      ]
    },
    "nullable": [
      true,
      false,
      false
    ]
  },
  "hash": "b48404872e4277d96071e708f035d21bbce210f4596fe44a6b2fb10d48d6341a"
}
